inceptiontube/__init__.py
inceptiontube-0.1.dist-info/LICENSE
inceptiontube-0.1.dist-info/METADATA
inceptiontube-0.1.dist-info/WHEEL
inceptiontube-0.1.dist-info/top_level.txt
inceptiontube-0.1.dist-info/RECORD
